astarconf/__init__.py
astarconf/cli.py
astarconf-0.1.4.dist-info/licenses/LICENSE
astarconf-0.1.4.dist-info/METADATA
astarconf-0.1.4.dist-info/WHEEL
astarconf-0.1.4.dist-info/entry_points.txt
astarconf-0.1.4.dist-info/top_level.txt
astarconf-0.1.4.dist-info/RECORD
