Metadata-Version: 2.4
Name: astarconf
Version: 0.1.4
Summary: A secure, pluggable config loader with encryption and CLI tools
Author-email: Andrey Starkov <astar@andreystarkov.com>
License: MIT
Project-URL: Repository, https://github.com/astaraiki/astarconf
Project-URL: Homepage, https://github.com/astaraiki/astarconf
Project-URL: Documentation, https://github.com/astaraiki/astarconf/blob/main/DOCUMENTATION.md
Project-URL: Contributing, https://github.com/astaraiki/astarconf/blob/main/CONTRIBUTING.md
Keywords: config,yaml,encryption,cli,dotenv,secure
Requires-Python: >=3.7
License-File: LICENSE
Requires-Dist: pyyaml
Requires-Dist: cryptography
Requires-Dist: python-dotenv
Dynamic: license-file
